pulsar_admin/__init__.py
pulsar_admin/backlog_quota.py
pulsar_admin/backlog_quota_type.py
pulsar_admin/clusters.py
pulsar_admin/clusters_test.py
pulsar_admin/http_client.py
pulsar_admin/http_client_test.py
pulsar_admin/message_id_impl.py
pulsar_admin/mode.py
pulsar_admin/namespaces.py
pulsar_admin/namespaces_test.py
pulsar_admin/p_admin.py
pulsar_admin/partitioned_topic_metadata.py
pulsar_admin/persistent_offline_topic_stats.py
pulsar_admin/persistent_topics.py
pulsar_admin/persistent_topics_test.py
pulsar_admin/pulsar_admin_exception.py
pulsar_admin/random_util.py
pulsar_admin/retention_policies.py
pulsar_admin/retention_policy.py
pulsar_admin/tenant_info.py
pulsar_admin/tenants.py
pulsar_admin/tenants_test.py
pulsar_admin/topic_version.py
pulsar_admin/url_const.py
pulsar_admin-0.0.2.dist-info/METADATA
pulsar_admin-0.0.2.dist-info/WHEEL
pulsar_admin-0.0.2.dist-info/top_level.txt
pulsar_admin-0.0.2.dist-info/RECORD
