Metadata-Version: 2.1
Name: pulsar_admin
Version: 0.0.2
Summary: A Python package for interacting with the Pulsar admin API
Home-page: https://github.com/protocol-laboratory/pulsar_admin
Author: shoothzj
Author-email: shoothzj@gmail.com
License: Apache License 2.0
Platform: UNKNOWN
Classifier: Programming Language :: Python :: 3
Classifier: Operating System :: OS Independent
Requires-Python: >=3.6
